phyra/__init__.py
phyra/cli.py
phyra/config.py
phyra/commands/__init__.py
phyra/commands/cmd_about.py
phyra/commands/cmd_bd.py
phyra/commands/cmd_game.py
phyra/commands/cmd_github.py
phyra/commands/cmd_hello.py
phyra/commands/cmd_search.py
phyra/commands/cmd_teledev.py
phyra/commands/cmd_weather.py
phyra/commands/cmd_wikipedia.py
phyra/commands/cmd_ytdl.py
phyra/service/__init__.py
phyra/service/svc_github.py
phyra/service/svc_weather.py
phyra/utilities/__init__.py
phyra/utilities/utils.py
phyra-1.6.7.dist-info/LICENSE
phyra-1.6.7.dist-info/METADATA
phyra-1.6.7.dist-info/WHEEL
phyra-1.6.7.dist-info/entry_points.txt
phyra-1.6.7.dist-info/top_level.txt
phyra-1.6.7.dist-info/RECORD
