Metadata-Version: 2.1
Name: phyra
Version: 1.6.7
Summary: A interactive CLI for programmer and everyone
Home-page: UNKNOWN
Author: LyQuid
Author-email: lyquidpersonal@gmail.com
License: Apache License 2.0
Platform: UNKNOWN
License-File: LICENSE
Requires-Dist: click
Requires-Dist: PyGithub
Requires-Dist: pyowm
Requires-Dist: pytest
Requires-Dist: ez-setup
Requires-Dist: pytube
Requires-Dist: setuptools
Requires-Dist: tqdm
Requires-Dist: google
Requires-Dist: beautifulsoup4
Requires-Dist: pyrogram
Requires-Dist: wikipedia
Requires-Dist: TgCrypto
